{
  "appPageId" : "5d4af12f-6fbb-49c3-8734-40f70e78fe21",
  "componentName" : "siteforce:sldsOneColLayout",
  "dataProviders" : [ ],
  "id" : "91e7ffec-cac3-4d73-bd07-ff4c119f15ff",
  "label" : "Record List",
  "regions" : [ {
    "id" : "d84d3931-d0bd-4147-ba25-747656c35464",
    "regionName" : "header",
    "type" : "region"
  }, {
    "components" : [ {
      "componentAttributes" : {
        "enableInlineEdit" : true,
        "filterName" : "{!filterId}",
        "layout" : "FULL",
        "pageSize" : 25,
        "scope" : "{!objectName}",
        "showActionBar" : true,
        "showChartsPanel" : true,
        "showDisplay" : "showall",
        "showFilterPanel" : true,
        "showImageIcon" : true,
        "showManualRefreshButton" : true,
        "showObjectName" : true,
        "showPinnedList" : true,
        "showSearchBar" : true
      },
      "componentName" : "forceCommunity:objectHome",
      "id" : "96b63cc6-11ff-4d6b-85e5-4be4e8bf13f7",
      "renderPriority" : "NEUTRAL",
      "renditionMap" : { },
      "type" : "component"
    } ],
    "id" : "9fd57371-2677-4dd9-b2ea-ac73ce64476e",
    "regionName" : "content",
    "type" : "region"
  }, {
    "id" : "19fc05d2-ded5-49ac-807e-fe74a8caf601",
    "regionName" : "footer",
    "type" : "region"
  } ],
  "themeLayoutType" : "Inner",
  "type" : "view",
  "viewType" : "list"
}